retry_iter.py
retry_iter-0.0.2.dist-info/LICENSE
retry_iter-0.0.2.dist-info/METADATA
retry_iter-0.0.2.dist-info/WHEEL
retry_iter-0.0.2.dist-info/top_level.txt
retry_iter-0.0.2.dist-info/RECORD
