Metadata-Version: 2.1
Name: retry-iter
Version: 0.0.2
Summary: Simple lib that provides retry helper as iterator
Home-page: https://gitlab.crnd.pro/crnd-opensource/retry-iter
Author: Center of Research & Development
Author-email: info@crnd.pro
License: MPL 2.0
Project-URL: Bug Tracker, https://crnd.pro/requests
Keywords: retry,iterator,iteration
Platform: UNKNOWN
Classifier: Development Status :: 3 - Alpha
Classifier: Intended Audience :: Developers
Classifier: License :: OSI Approved :: Mozilla Public License 2.0 (MPL 2.0)
Classifier: Programming Language :: Python
Classifier: Programming Language :: Python :: 3
Classifier: Programming Language :: Python :: 3.6
Classifier: Programming Language :: Python :: 3.7
Classifier: Programming Language :: Python :: 3.8
Classifier: Programming Language :: Python :: 3.9
Classifier: Programming Language :: Python :: Implementation :: CPython
Classifier: Topic :: Utilities
Classifier: Topic :: Software Development :: Libraries
Classifier: Topic :: Software Development :: Libraries :: Python Modules
Requires-Python: >=3.6
License-File: LICENSE
